svirl/__init__.py
svirl/config.py
svirl/plotter.py
svirl/cuda/block_reduction.h
svirl/cuda/cg.h
svirl/cuda/common.h
svirl/cuda/observables.h
svirl/cuda/reduction.h
svirl/cuda/td.h
svirl/cuda/utils.h
svirl/mesh/__init__.py
svirl/mesh/grid.py
svirl/observables/__init__.py
svirl/observables/observables.py
svirl/observables/vortex_detector.py
svirl/parallel/__init__.py
svirl/parallel/reduction.py
svirl/parallel/startup.py
svirl/parallel/utils.py
svirl/solvers/__init__.py
svirl/solvers/cg.py
svirl/solvers/solvers.py
svirl/solvers/td.py
svirl/storage/__init__.py
svirl/storage/arrays.py
svirl/vars/__init__.py
svirl/vars/fixed_vortices.py
svirl/vars/params.py
svirl/vars/vars.py
svirl-1.0.dist-info/AUTHORS
svirl-1.0.dist-info/LICENSE
svirl-1.0.dist-info/METADATA
svirl-1.0.dist-info/NOTICE.txt
svirl-1.0.dist-info/WHEEL
svirl-1.0.dist-info/top_level.txt
svirl-1.0.dist-info/RECORD
