Metadata-Version: 2.1
Name: svirl
Version: 1.0
Summary: GPU accelerated Ginzburg-Landau equations solver
Home-page: UNKNOWN
Maintainer: Shriram Jagannathan, Ivan Sadovskyy
Maintainer-email: svirl@outlook.com
License: MIT
Platform: UNKNOWN
